hf_kernels/__init__.py
hf_kernels/utils.py
hf_kernels/build.py
hf_kernels-0.1.0.dist-info/WHEEL
hf_kernels-0.1.0.dist-info/METADATA
hf_kernels-0.1.0.dist-info/RECORD
