Metadata-Version: 2.3
Name: hf-kernels
Version: 0.1.0
Summary: Download cuda kernels
Author: OlivierDehaene, Daniel de Kok, David Holtz, Nicolas Patry
Author-email: OlivierDehaene <olivier@huggingface.co>, Daniel de Kok <daniel@huggingface.co>, David Holtz <david@huggingface.co>, Nicolas Patry <nicolas@huggingface.co>
